smote_variants/__init__.py
smote_variants/_logger.py
smote_variants/_version.py
smote_variants/config.py
smote_variants/base/__init__.py
smote_variants/base/_base.py
smote_variants/base/_metrics.py
smote_variants/base/_metrictensor.py
smote_variants/base/_oversampling.py
smote_variants/base/_scipyport.py
smote_variants/base/_simplexsampling.py
smote_variants/base/_undersampling.py
smote_variants/classifiers/__init__.py
smote_variants/classifiers/_errorwarning_classifier.py
smote_variants/classifiers/_mlpclassifierwrapper.py
smote_variants/classifiers/_oversamplingclassifier.py
smote_variants/datasets/__init__.py
smote_variants/datasets/_datasets.py
smote_variants/evaluation/__init__.py
smote_variants/evaluation/_evaluation.py
smote_variants/evaluation/_folding.py
smote_variants/evaluation/_functions.py
smote_variants/evaluation/_parallelization.py
smote_variants/evaluation/_processing.py
smote_variants/evaluation/_sampling.py
smote_variants/multiclassoversampling/__init__.py
smote_variants/multiclassoversampling/_multiclassoversampling.py
smote_variants/noise_removal/__init__.py
smote_variants/noise_removal/_cnntomeklinks.py
smote_variants/noise_removal/_condensednn.py
smote_variants/noise_removal/_editednn.py
smote_variants/noise_removal/_neighborhoodcleaningrule.py
smote_variants/noise_removal/_noisefilter.py
smote_variants/noise_removal/_onesidedselection.py
smote_variants/noise_removal/_tomeklinkremoval.py
smote_variants/oversampling/__init__.py
smote_variants/oversampling/_a_suwo.py
smote_variants/oversampling/_adasyn.py
smote_variants/oversampling/_adg.py
smote_variants/oversampling/_adoms.py
smote_variants/oversampling/_ahc.py
smote_variants/oversampling/_amsco.py
smote_variants/oversampling/_and_smote.py
smote_variants/oversampling/_ans.py
smote_variants/oversampling/_asmobd.py
smote_variants/oversampling/_assembled_smote.py
smote_variants/oversampling/_borderline_smote.py
smote_variants/oversampling/_cbso.py
smote_variants/oversampling/_ccr.py
smote_variants-1.0.1.dist-info/LICENSE
smote_variants-1.0.1.dist-info/METADATA
smote_variants-1.0.1.dist-info/WHEEL
smote_variants-1.0.1.dist-info/top_level.txt
smote_variants-1.0.1.dist-info/RECORD
