Metadata-Version: 2.1
Name: smote_variants
Version: 1.0.1
Summary: Variants of the synthetic minority oversampling technique (SMOTE) for imbalanced learning
Home-page: https://github.com/analyticalmindsltd/smote_variants
Download-URL: https://github.com/analyticalmindsltd/smote_variants
Author: Gyorgy Kovacs
Author-email: gyuriofkovacs@gmail.com
Maintainer: Gyorgy Kovacs
Maintainer-email: gyuriofkovacs@gmail.com
License: MIT
Classifier: Intended Audience :: Science/Research
Classifier: Intended Audience :: Developers
Classifier: Development Status :: 3 - Alpha
Classifier: License :: OSI Approved :: MIT License
Classifier: Programming Language :: Python
Classifier: Topic :: Scientific/Engineering :: Artificial Intelligence
Classifier: Topic :: Software Development
Classifier: Operating System :: Microsoft :: Windows
Classifier: Operating System :: POSIX
Classifier: Operating System :: Unix
Classifier: Operating System :: MacOS
Requires-Python: >=3.5
License-File: LICENSE
Requires-Dist: numpy
Requires-Dist: scipy
Requires-Dist: scikit-learn
Requires-Dist: joblib
Requires-Dist: minisom
Requires-Dist: statistics
Requires-Dist: tensorflow
Requires-Dist: keras
Requires-Dist: pandas
Requires-Dist: mkl
Requires-Dist: metric_learn
Requires-Dist: seaborn
Provides-Extra: tests
Requires-Dist: pytest; extra == "tests"
Provides-Extra: docs
Requires-Dist: sphinx; extra == "docs"
Requires-Dist: sphinx-gallery; extra == "docs"
Requires-Dist: sphinx_rtd_theme; extra == "docs"
Requires-Dist: matplotlib; extra == "docs"
Requires-Dist: pandas; extra == "docs"
